<annotation>
	<folder></folder>
	<filename>ISIC_0010611_jpg.rf.f5168c4844ca50a716878f719b2fe31a.jpg</filename>
	<path>ISIC_0010611_jpg.rf.f5168c4844ca50a716878f719b2fe31a.jpg</path>
	<source>
		<database>roboflow.com</database>
	</source>
	<size>
		<width>640</width>
		<height>640</height>
		<depth>3</depth>
	</size>
	<segmented>0</segmented>
	<object>
		<name>melanoma</name>
		<pose>Unspecified</pose>
		<truncated>0</truncated>
		<difficult>0</difficult>
		<occluded>0</occluded>
		<bndbox>
			<xmin>31</xmin>
			<xmax>538</xmax>
			<ymin>6</ymin>
			<ymax>608</ymax>
		</bndbox>
	</object>
	<metadata>
	</metadata>
</annotation>
