<annotation>
	<folder></folder>
	<filename>ISIC_0033762_jpg.rf.1c9db47de4b9843cad8be3e72c442394.jpg</filename>
	<path>ISIC_0033762_jpg.rf.1c9db47de4b9843cad8be3e72c442394.jpg</path>
	<source>
		<database>roboflow.com</database>
	</source>
	<size>
		<width>640</width>
		<height>640</height>
		<depth>3</depth>
	</size>
	<segmented>0</segmented>
	<object>
		<name>vascular lesion</name>
		<pose>Unspecified</pose>
		<truncated>0</truncated>
		<difficult>0</difficult>
		<occluded>0</occluded>
		<bndbox>
			<xmin>185</xmin>
			<xmax>532</xmax>
			<ymin>56</ymin>
			<ymax>446</ymax>
		</bndbox>
	</object>
	<metadata>
	</metadata>
</annotation>
