<annotation>
	<folder></folder>
	<filename>ISIC_0026717_jpg.rf.8540dd0fe6f07132bd3010659cec488c.jpg</filename>
	<path>ISIC_0026717_jpg.rf.8540dd0fe6f07132bd3010659cec488c.jpg</path>
	<source>
		<database>roboflow.com</database>
	</source>
	<size>
		<width>640</width>
		<height>640</height>
		<depth>3</depth>
	</size>
	<segmented>0</segmented>
	<object>
		<name>pigmented benign keratosis</name>
		<pose>Unspecified</pose>
		<truncated>0</truncated>
		<difficult>0</difficult>
		<occluded>0</occluded>
		<bndbox>
			<xmin>174</xmin>
			<xmax>480</xmax>
			<ymin>73</ymin>
			<ymax>534</ymax>
		</bndbox>
	</object>
	<metadata>
	</metadata>
</annotation>
