<annotation>
	<folder></folder>
	<filename>ISIC_0033810_jpg.rf.6e20eff53a27df7f2a4f9c729a7a5efa.jpg</filename>
	<path>ISIC_0033810_jpg.rf.6e20eff53a27df7f2a4f9c729a7a5efa.jpg</path>
	<source>
		<database>roboflow.com</database>
	</source>
	<size>
		<width>640</width>
		<height>640</height>
		<depth>3</depth>
	</size>
	<segmented>0</segmented>
	<object>
		<name>dermatofibroma</name>
		<pose>Unspecified</pose>
		<truncated>0</truncated>
		<difficult>0</difficult>
		<occluded>0</occluded>
		<bndbox>
			<xmin>202</xmin>
			<xmax>450</xmax>
			<ymin>137</ymin>
			<ymax>544</ymax>
		</bndbox>
	</object>
	<metadata>
	</metadata>
</annotation>
