<annotation>
	<folder></folder>
	<filename>ISIC_0000363_jpg.rf.1eaf56939595af0ca2d9ef50c25b5336.jpg</filename>
	<path>ISIC_0000363_jpg.rf.1eaf56939595af0ca2d9ef50c25b5336.jpg</path>
	<source>
		<database>roboflow.com</database>
	</source>
	<size>
		<width>640</width>
		<height>640</height>
		<depth>3</depth>
	</size>
	<segmented>0</segmented>
	<object>
		<name>Skin-Cancer</name>
		<pose>Unspecified</pose>
		<truncated>0</truncated>
		<difficult>0</difficult>
		<occluded>0</occluded>
		<bndbox>
			<xmin>176</xmin>
			<xmax>524</xmax>
			<ymin>166</ymin>
			<ymax>549</ymax>
		</bndbox>
	</object>
	<metadata>
		<tags>
			<tag>Cancer</tag>
		</tags>
	</metadata>
</annotation>
